<Material name="FlatShading">
	<Sampler name="LinearSampler">
		<State name="Filter" value=""/>
		<State name="AddressU" value=""/>
		<State name="AddressV" value=""/>
		<State name="AddressW" value=""/>
		<State name="MaxAnisotropy" value=""/>
		<State name="MinLod" value=""/>
		<State name="MaxLod" value=""/>
		<State name="MipMapLODBias" value=""/>
		<State name="ComparisonFunc" value=""/>
		<State name="BorderColor" r="" g="" b="" a=""/>
	</Sampler>
	
	<Parameter type="float4x4" name="World" semantic="WorldMatrix" />
	<Parameter type="float4x4" name="ViewProj" semantic="ViewProjectionMatrix" />
	<Parameter type="texture2d" name="DiffuseMap" semantic="DiffuseMaterialMap" stage="PixelShader" sampler="LinearSampler", value=""/>
	
	<Effect name="SimpleTextured" file="../Media/Effects/SimpleTextured.effect.xml">
		<Technique name="PhongLight" />
	</Effect>
</Material>